pyobs_aravis/__init__.py
pyobs_aravis/aravis.py
pyobs_aravis/araviscamera.py
pyobs_aravis-1.1.4.dist-info/METADATA
pyobs_aravis-1.1.4.dist-info/WHEEL
pyobs_aravis-1.1.4.dist-info/licenses/LICENSE
pyobs_aravis-1.1.4.dist-info/RECORD
