Metadata-Version: 2.4
Name: pyobs-aravis
Version: 1.1.4
Summary: pyobs module for Aravis cameras
Author-email: Tim-Oliver Husser <thusser@uni-goettingen.de>
License-Expression: MIT
License-File: LICENSE
Requires-Python: >=3.11
Requires-Dist: numpy~=1.21
Requires-Dist: pygobject~=3.42
Requires-Dist: pyobs-core~=1.0
